oscillator/__init__.py
oscillator/oscillator.py
oscillator_gym-1.2.3.dist-info/WHEEL
oscillator_gym-1.2.3.dist-info/METADATA
oscillator_gym-1.2.3.dist-info/RECORD
