Metadata-Version: 2.1
Name: oscillator-gym
Version: 1.2.3
Summary: A flexible harmonic oscillator environment for OpenAI Gym
Author: Onno Eberhard
Author-email: onnoeberhard@gmail.com
Requires-Python: >=3.7,<4.0
Classifier: Programming Language :: Python :: 3
Classifier: Programming Language :: Python :: 3.10
Classifier: Programming Language :: Python :: 3.7
Classifier: Programming Language :: Python :: 3.8
Classifier: Programming Language :: Python :: 3.9
Requires-Dist: gym (>=0.22,<1.0)
Requires-Dist: numpy
Requires-Dist: pygame
